naampy/__init__.py
naampy/in_rolls_fn.py
naampy/utils.py
naampy/model/naampy_rmse/keras_metadata.pb
naampy/model/naampy_rmse/saved_model.pb
naampy/model/naampy_rmse/variables/variables.data-00000-of-00001
naampy/model/naampy_rmse/variables/variables.index
naampy-0.6.1.dist-info/licenses/LICENSE
naampy-0.6.1.dist-info/METADATA
naampy-0.6.1.dist-info/WHEEL
naampy-0.6.1.dist-info/entry_points.txt
naampy-0.6.1.dist-info/top_level.txt
naampy-0.6.1.dist-info/RECORD
